multiwordnet/__init__.py
multiwordnet/wordnet.py
multiwordnet/db/__init__.py
multiwordnet/db/common/common_relation.sql
multiwordnet/db/common/common_semfield.sql
multiwordnet/db/common/common_semfield_hierarchy.sql
multiwordnet/db/common/common_sentiment.sql
multiwordnet/db/english/english_index.sql
multiwordnet/db/english/english_lemma.sql
multiwordnet/db/english/english_relation.sql
multiwordnet/db/english/english_synset.sql
multiwordnet/db/french/french_index.sql
multiwordnet/db/french/french_lemma.sql
multiwordnet/db/french/french_synset.sql
multiwordnet/db/hebrew/hebrew_index.sql
multiwordnet/db/hebrew/hebrew_lemma.sql
multiwordnet/db/hebrew/hebrew_morpho.sql
multiwordnet/db/hebrew/hebrew_relation.sql
multiwordnet/db/hebrew/hebrew_synonyms.sql
multiwordnet/db/hebrew/hebrew_synset.sql
multiwordnet/db/italian/italian_index.sql
multiwordnet/db/italian/italian_lemma.sql
multiwordnet/db/italian/italian_synset.sql
multiwordnet/db/latin/latin_index.sql
multiwordnet/db/latin/latin_lemma.sql
multiwordnet/db/latin/latin_morpho.sql
multiwordnet/db/latin/latin_relation.sql
multiwordnet/db/latin/latin_synonyms.sql
multiwordnet/db/latin/latin_synset.sql
multiwordnet/db/portuguese/portuguese_index.sql
multiwordnet/db/portuguese/portuguese_lemma.sql
multiwordnet/db/portuguese/portuguese_synset.sql
multiwordnet/db/spanish/spanish_index.sql
multiwordnet/db/spanish/spanish_lemma.sql
multiwordnet/db/spanish/spanish_synset.sql
multiwordnet-0.1.5.dist-info/LICENSE
multiwordnet-0.1.5.dist-info/METADATA
multiwordnet-0.1.5.dist-info/WHEEL
multiwordnet-0.1.5.dist-info/top_level.txt
multiwordnet-0.1.5.dist-info/RECORD
