Metadata-Version: 2.1
Name: multiwordnet
Version: 0.1.5
Summary: A helper library for accessing and manipulating WordNets in the MultiWordNet
Home-page: UNKNOWN
Author: William Michael Short
Author-email: w.short@exeter.ac.uk
License: Attribution-ShareAlike 4.0 International (CC BY-SA 4.0)
Platform: UNKNOWN
Requires-Python: >=3.5
Requires-Dist: tqdm (>=4.41.1)
